CRR/__init__.py
CRR/api/__init__.py
CRR/api/api.py
CRR/db/GenerateCsv.py
CRR/db/__init__.py
CRR/db/data_generator.py
CRR/db/db.py
CRR/model/__init__.py
CRR/model/model.py
CRR/model/plots.py
CRR-0.0.3.dist-info/LICENSE
CRR-0.0.3.dist-info/METADATA
CRR-0.0.3.dist-info/WHEEL
CRR-0.0.3.dist-info/top_level.txt
CRR-0.0.3.dist-info/RECORD
