Metadata-Version: 2.1
Name: CRR
Version: 0.0.3
Summary: Tool for doing retention rate analysis
Author: Areg Hovakimyan, Arutiun Dzhilavyan, Karen Sahakyan, Leonid Sarkisyan, Melik Tigranyan
Classifier: Development Status :: 3 - Alpha
Requires-Python: >=3.10, <3.12
License-File: LICENSE
Requires-Dist: annotated-types ==0.6.0
Requires-Dist: anyio ==4.3.0
Requires-Dist: appnope ==0.1.4
Requires-Dist: asttokens ==2.4.1
Requires-Dist: click ==8.1.7
Requires-Dist: comm ==0.2.2
Requires-Dist: debugpy ==1.8.1
Requires-Dist: decorator ==5.1.1
Requires-Dist: exceptiongroup ==1.2.0
Requires-Dist: executing ==2.0.1
Requires-Dist: Faker ==24.8.0
Requires-Dist: fastapi ==0.110.1
Requires-Dist: ghp-import ==2.1.0
Requires-Dist: h11 ==0.14.0
Requires-Dist: idna ==3.6
Requires-Dist: install ==1.3.5
Requires-Dist: ipykernel ==6.29.4
Requires-Dist: ipython ==8.23.0
Requires-Dist: jedi ==0.19.1
Requires-Dist: Jinja2 ==3.1.3
Requires-Dist: joblib ==1.4.0
Requires-Dist: jupyter-client ==8.6.1
Requires-Dist: jupyter-core ==5.7.2
Requires-Dist: Markdown ==3.6
Requires-Dist: MarkupSafe ==2.1.5
Requires-Dist: matplotlib-inline ==0.1.6
Requires-Dist: mergedeep ==1.3.4
Requires-Dist: mkdocs ==1.6.0
Requires-Dist: mkdocs-get-deps ==0.2.0
Requires-Dist: nest-asyncio ==1.6.0
Requires-Dist: numpy ==1.26.4
Requires-Dist: packaging ==24.0
Requires-Dist: pandas ==2.2.1
Requires-Dist: parso ==0.8.4
Requires-Dist: pathspec ==0.12.1
Requires-Dist: pexpect ==4.9.0
Requires-Dist: platformdirs ==4.2.0
Requires-Dist: prompt-toolkit ==3.0.43
Requires-Dist: psutil ==5.9.8
Requires-Dist: ptyprocess ==0.7.0
Requires-Dist: pure-eval ==0.2.2
Requires-Dist: pydantic ==2.6.4
Requires-Dist: pydantic-core ==2.16.3
Requires-Dist: Pygments ==2.17.2
Requires-Dist: python-dateutil ==2.9.0.post0
Requires-Dist: pytz ==2024.1
Requires-Dist: PyYAML ==6.0.1
Requires-Dist: pyyaml-env-tag ==0.1
Requires-Dist: pyzmq ==25.1.2
Requires-Dist: scikit-learn ==1.4.1.post1
Requires-Dist: scipy ==1.13.0
Requires-Dist: six ==1.16.0
Requires-Dist: sniffio ==1.3.1
Requires-Dist: SQLAlchemy ==2.0.29
Requires-Dist: stack-data ==0.6.3
Requires-Dist: starlette ==0.37.2
Requires-Dist: threadpoolctl ==3.4.0
Requires-Dist: tornado ==6.4
Requires-Dist: traitlets ==5.14.2
Requires-Dist: typing-extensions ==4.11.0
Requires-Dist: tzdata ==2024.1
Requires-Dist: uvicorn ==0.29.0
Requires-Dist: watchdog ==4.0.0
Requires-Dist: wcwidth ==0.2.13
